README.md
setup.py
journalMiner/__init__.py
journalMiner/_version.py
journalMiner/pyminer.py
journal_miner.egg-info/PKG-INFO
journal_miner.egg-info/SOURCES.txt
journal_miner.egg-info/dependency_links.txt
journal_miner.egg-info/entry_points.txt
journal_miner.egg-info/requires.txt
journal_miner.egg-info/top_level.txt