Metadata-Version: 1.0
Name: journal-miner
Version: 1.5
Summary: Python CLI for mining scientific literature.
Home-page: https://github.com/J-E-J-S/pyminer
Author: George Pearse, James Sanders
Author-email: james.sanders1711@gmail.com
License: UNKNOWN
Platform: UNKNOWN
